noxqs/__init__.py
noxqs/noxqs.py
noxqs-0.0.2.dist-info/LICENSE
noxqs-0.0.2.dist-info/METADATA
noxqs-0.0.2.dist-info/WHEEL
noxqs-0.0.2.dist-info/top_level.txt
noxqs-0.0.2.dist-info/RECORD
