Metadata-Version: 2.1
Name: noxqs
Version: 0.0.2
Summary: NoXQS::No Excuse - personal swiss pocket knife
Author-email: Morgan Heijdemann <targhan@gmail.com>
License: Copyright (c) 2018 The Python Packaging Authority        
Classifier: Programming Language :: Python :: 3
Classifier: License :: OSI Approved :: MIT License
Classifier: Operating System :: OS Independent
Requires-Python: >=3.7
License-File: LICENSE
